LICENSE.txt
MANIFEST.in
README.rst
setup.py
gj2ascii/__init__.py
gj2ascii/cli.py
gj2ascii/core.py
gj2ascii/pycompat.py
gj2ascii.egg-info/PKG-INFO
gj2ascii.egg-info/SOURCES.txt
gj2ascii.egg-info/dependency_links.txt
gj2ascii.egg-info/entry_points.txt
gj2ascii.egg-info/requires.txt
gj2ascii.egg-info/top_level.txt
gj2ascii.egg-info/zip-safe
tests/__init__.py
tests/test_cli.py
tests/test_core.py