Metadata-Version: 1.1
Name: gj2ascii
Version: 0.4
Summary: Render GeoJSON as ASCII on the commandline.
Home-page: https://github.com/geowurster/gj2ascii
Author: Kevin Wurster
Author-email: wursterk@gmail.com
License: New BSD License
